[
    {
        "id": "bbf3f3e1-B7c5-4d56-8fdd-ff6f3d1e9a2a",
        "username": "user",
        "email": "user@mail.com",
        "authorities": ["ROLE_USER"],
        "enabled": true,
        "failedLoginAttempts": 0,
        "createdAt": "2024-01-01T12:00:00.000Z",
        "updatedAt": "2024-01-01T12:00:00.000Z",
        "accountNonLocked": true,
        "avatar": "https://primefaces.org/cdn/primevue/images/avatar/ionibowcher.png"
    },
    {
        "id": "1080cf43-f931-416f-8aeb-ced8b0922edc",
        "username": "testuser",
        "email": "test@mail.com",
        "authorities": ["ROLE_USER"],
        "enabled": true,
        "failedLoginAttempts": 0,
        "createdAt": "2024-01-01T12:00:00.000Z",
        "updatedAt": "2024-01-01T12:00:00.000Z",
        "accountNonLocked": true,
        "avatar": "https://primefaces.org/cdn/primevue/images/avatar/amyelsner.png"
    },
    {
        "id": "2e083c48-289b-4357-9d70-9832dec6e95b",
        "username": "adminuser",
        "email": "admin@mail.com",
        "authorities": ["ROLE_USER", "ROLE_ADMIN"],
        "enabled": true,
        "failedLoginAttempts": 0,
        "createdAt": "2024-01-01T12:00:00.000Z",
        "updatedAt": "2024-01-01T12:00:00.000Z",
        "accountNonLocked": true,
        "avatar": "https://primefaces.org/cdn/primevue/images/avatar/xuxuefeng.png"
    },
    {
        "id": "e212f8da-8256-4762-bc09-e6ae20b98c23",
        "username": "sven_goteborg",
        "email": "sven@mail.se",
        "authorities": ["ROLE_USER"],
        "enabled": true,
        "failedLoginAttempts": 0,
        "createdAt": "2024-01-01T12:00:00.000Z",
        "updatedAt": "2024-01-01T12:00:00.000Z",
        "accountNonLocked": true,
        "avatar": "https://primefaces.org/cdn/primevue/images/avatar/asiyajavayant.png"
    },
    {
        "id": "6c9a1907-cf69-40c2-81d1-5599c652b6ce",
        "username": "karin_k",
        "email": "karin@mail.se",
        "authorities": ["ROLE_USER"],
        "enabled": true,
        "failedLoginAttempts": 0,
        "createdAt": "2024-01-01T12:00:00.000Z",
        "updatedAt": "2024-01-01T12:00:00.000Z",
        "accountNonLocked": true,
        "avatar": "https://primefaces.org/cdn/primevue/images/avatar/annafali.png"
    },
    {
        "id": "4cd33f07-1f55-4cd8-9195-a0548e586e19",
        "username": "olof_p",
        "email": "olof@mail.se",
        "authorities": ["ROLE_USER"],
        "enabled": true,
        "failedLoginAttempts": 0,
        "createdAt": "2024-01-01T12:00:00.000Z",
        "updatedAt": "2024-01-01T12:00:00.000Z",
        "accountNonLocked": true,
        "avatar": "https://primefaces.org/cdn/primevue/images/avatar/onyamalimba.png"
    }
]
